odoo/addons/hr_holidays_accrual_advanced/README.rst
odoo/addons/hr_holidays_accrual_advanced/__init__.py
odoo/addons/hr_holidays_accrual_advanced/__manifest__.py
odoo/addons/hr_holidays_accrual_advanced/i18n/fr.po
odoo/addons/hr_holidays_accrual_advanced/i18n/hr_holidays_accrual_advanced.pot
odoo/addons/hr_holidays_accrual_advanced/models/__init__.py
odoo/addons/hr_holidays_accrual_advanced/models/hr_leave.py
odoo/addons/hr_holidays_accrual_advanced/models/hr_leave_allocation.py
odoo/addons/hr_holidays_accrual_advanced/models/hr_leave_allocation_accruement.py
odoo/addons/hr_holidays_accrual_advanced/models/resource_calendar_leaves.py
odoo/addons/hr_holidays_accrual_advanced/readme/CONTRIBUTORS.rst
odoo/addons/hr_holidays_accrual_advanced/readme/DESCRIPTION.rst
odoo/addons/hr_holidays_accrual_advanced/readme/ROADMAP.rst
odoo/addons/hr_holidays_accrual_advanced/readme/USAGE.rst
odoo/addons/hr_holidays_accrual_advanced/security/hr_holidays_accrual_security.xml
odoo/addons/hr_holidays_accrual_advanced/security/ir.model.access.csv
odoo/addons/hr_holidays_accrual_advanced/static/description/icon.png
odoo/addons/hr_holidays_accrual_advanced/static/description/index.html
odoo/addons/hr_holidays_accrual_advanced/tests/__init__.py
odoo/addons/hr_holidays_accrual_advanced/tests/test_hr_holidays_accrual_advanced.py
odoo/addons/hr_holidays_accrual_advanced/views/hr_leave_allocation.xml
odoo/addons/hr_holidays_accrual_advanced/views/hr_leave_allocation_accruement.xml
odoo/addons/hr_holidays_accrual_advanced/wizards/__init__.py
odoo/addons/hr_holidays_accrual_advanced/wizards/hr_leave_allocation_accrual_calculator.py
odoo/addons/hr_holidays_accrual_advanced/wizards/hr_leave_allocation_accrual_calculator.xml
odoo12_addon_hr_holidays_accrual_advanced-12.0.1.0.2.dist-info/METADATA
odoo12_addon_hr_holidays_accrual_advanced-12.0.1.0.2.dist-info/WHEEL
odoo12_addon_hr_holidays_accrual_advanced-12.0.1.0.2.dist-info/top_level.txt
odoo12_addon_hr_holidays_accrual_advanced-12.0.1.0.2.dist-info/RECORD
